{
    "title": "The Most Popular Holiday Recipe From Each U.S. State",
    "file_name": "the-most-popular-holiday-recipe-from-each-us-state",
    "url": "https://www.allrecipes.com/the-most-popular-holiday-recipe-from-each-us-state-8761237",
    "cuisine": "Russian",
    "difficulty": "Medium",
    "cooking_time": "60 minutes",
    "country": "Russia",
    "continent": "Europe/Asia",
    "metadata": {
        "prep_time": "Unknown",
        "cook_time": "Unknown",
        "total_time": "Unknown",
        "active_time": "Unknown",
        "servings": "Unknown",
        "calories": "Unknown"
    },
    "ingredients": [],
    "method": [],
    "image": "images/the-most-popular-holiday-recipe-from-each-us-state.jpg"
}